Workbook

Sheet Dashboard
A1: Dashboard
A2: Everything below recalculates automatically from Transactions, Accounts, and Categories.
A4: Month to analyze (YYYY-MM): | C4: =TEXT(TODAY(),"YYYY-MM") -> 2026-08
A6: Net Worth | C6: Income This Month | E6: Spending This Month
A7: =Accounts!$B$51 -> 42900 | C7: =SUMIFS(Transactions!$F$5:$F$500,Transactions!$L$5:$L$500,Dashboard!$C$4,Transactions!$M$5:$M$500,"Income") -> 0 | E7: =-(SUMIFS(Transactions!$I$5:$I$500,Transactions!$L$5:$L$500,Dashboard!$C$4,Transactions!$M$5:$M$500,"Needs")+SUMIFS(Transactions!$I$5:$I$500,Transactions!$L$5:$L$500,Dashboard!$C$4,Transactions!$M$5:$M$500,"Wants")) -> 0
A9: Owed to Me (net, all-time)
A10: =SUM(Transactions!H5:H500)-SUMIFS(Transactions!F5:F500,Transactions!E5:E500,"Reimbursement") -> 40
A13: Category | B13: Group | C13: Monthly Budget | D13: Actual Spent | E13: Remaining
A14: =Categories!A5 -> Groceries | B14: Needs | C14: =Categories!C5 -> 500 | D14: =-SUMIFS(Transactions!$I$5:$I$500,Transactions!$L$5:$L$500,Dashboard!$C$4,Transactions!$E$5:$E$500,A14) -> 0 | E14: =C14-D14 -> 500
A15: =Categories!A6 -> Dining Out | B15: Wants | C15: =Categories!C6 -> 200 | D15: =-SUMIFS(Transactions!$I$5:$I$500,Transactions!$L$5:$L$500,Dashboard!$C$4,Transactions!$E$5:$E$500,A15) -> 0 | E15: =C15-D15 -> 200
A16: =Categories!A7 -> Transport | B16: Needs | C16: =Categories!C7 -> 150 | D16: =-SUMIFS(Transactions!$I$5:$I$500,Transactions!$L$5:$L$500,Dashboard!$C$4,Transactions!$E$5:$E$500,A16) -> 0 | E16: =C16-D16 -> 150
A17: =Categories!A8 -> Rent/Mortgage | B17: Needs | C17: =Categories!C8 -> 1800 | D17: =-SUMIFS(Transactions!$I$5:$I$500,Transactions!$L$5:$L$500,Dashboard!$C$4,Transactions!$E$5:$E$500,A17) -> 0 | E17: =C17-D17 -> 1800
A18: =Categories!A9 -> Utilities | B18: Needs | C18: =Categories!C9 -> 200 | D18: =-SUMIFS(Transactions!$I$5:$I$500,Transactions!$L$5:$L$500,Dashboard!$C$4,Transactions!$E$5:$E$500,A18) -> 0 | E18: =C18-D18 -> 200
A19: =Categories!A10 -> Entertainment | B19: Wants | C19: =Categories!C10 -> 100 | D19: =-SUMIFS(Transactions!$I$5:$I$500,Transactions!$L$5:$L$500,Dashboard!$C$4,Transactions!$E$5:$E$500,A19) -> 0 | E19: =C19-D19 -> 100
A20: =Categories!A11 -> Shopping | B20: Wants | C20: =Categories!C11 -> 150 | D20: =-SUMIFS(Transactions!$I$5:$I$500,Transactions!$L$5:$L$500,Dashboard!$C$4,Transactions!$E$5:$E$500,A20) -> 0 | E20: =C20-D20 -> 150
A21: =Categories!A12 -> Health | B21: Needs | C21: =Categories!C12 -> 100 | D21: =-SUMIFS(Transactions!$I$5:$I$500,Transactions!$L$5:$L$500,Dashboard!$C$4,Transactions!$E$5:$E$500,A21) -> 0 | E21: =C21-D21 -> 100
A22: =Categories!A13 -> Travel | B22: Wants | C22: =Categories!C13 -> 100 | D22: =-SUMIFS(Transactions!$I$5:$I$500,Transactions!$L$5:$L$500,Dashboard!$C$4,Transactions!$E$5:$E$500,A22) -> 0 | E22: =C22-D22 -> 100
A23: =Categories!A14 -> Subscriptions | B23: Wants | C23: =Categories!C14 -> 50 | D23: =-SUMIFS(Transactions!$I$5:$I$500,Transactions!$L$5:$L$500,Dashboard!$C$4,Transactions!$E$5:$E$500,A23) -> 0 | E23: =C23-D23 -> 50
A24: =Categories!A15 -> Miscellaneous Expenses | B24: Wants | C24: =Categories!C15 -> 100 | D24: =-SUMIFS(Transactions!$I$5:$I$500,Transactions!$L$5:$L$500,Dashboard!$C$4,Transactions!$E$5:$E$500,A24) -> 0 | E24: =C24-D24 -> 100
A27: Needs / Wants / Savings Split
A28: Planned Monthly Income (take-home; mostly salary) | B28: Edit this -> | C28: =SUMIFS(Categories!$C$5:$C$60,Categories!$B$5:$B$60,"Income") -> 6000
A30: Group | B30: Planned % | C30: Planned $ | D30: Actual $ | E30: Actual %
A31: Needs | B31: 0.5 | C31: =B31*$C$28 -> 3000 | D31: =IF($C$4="","",-SUMIFS(Transactions!$I$5:$I$500,Transactions!$L$5:$L$500,$C$4,Transactions!$M$5:$M$500,"Needs")) -> 0 | E31: =IFERROR(D31/$C$7,0) -> 0
A32: Wants | B32: 0.3 | C32: =B32*$C$28 -> 1800 | D32: =IF($C$4="","",-SUMIFS(Transactions!$I$5:$I$500,Transactions!$L$5:$L$500,$C$4,Transactions!$M$5:$M$500,"Wants")) -> 0 | E32: =IFERROR(D32/$C$7,0) -> 0
A33: Savings | B33: 0.2 | C33: =B33*$C$28 -> 1200 | D33: =IF($C$4="","",-SUMIFS(Transactions!$I$5:$I$500,Transactions!$L$5:$L$500,$C$4,Transactions!$M$5:$M$500,"Savings")) -> 0 | E33: =IFERROR(D33/$C$7,0) -> 0
A34: Total | B34: =SUM(B31:B33) -> 1 | C34: =SUM(C31:C33) -> 6000 | D34: =SUM(D31:D33) -> 0 | E34: =SUM(E31:E33) -> 0

Sheet Transactions
A1: Transactions
A2: Log every transaction here (manually, pasted from a bank CSV, or via the optional Plaid sync). See README for the reimbursement / internal transfer / savings workflow.
A4: Txn ID | B4: Date | C4: Account | D4: Merchant / Description | E4: Category | F4: Amount | G4: Status | H4: Reimbursable Amount | I4: Net Amount | J4: Linked Txn ID (optional) | K4: Notes | L4: Month | M4: Group
A5: =IF(B5="","","T"&TEXT(ROW()-4,"0000")) -> T0001 | B5: 2026-01-01 | C5: Checking - Bank A | D5: Paycheck | E5: Salary | F5: 6000 | G5: Normal | H5: 0 | I5: =IF(F5="","",F5+H5) -> 6000 | K5: Monthly salary | L5: =IF(B5="","",TEXT(B5,"YYYY-MM")) -> 2026-01 | M5: =IF($E5="","",IFERROR(VLOOKUP($E5,Categories!$A:$B,2,FALSE()),"")) -> Income
A6: =IF(B6="","","T"&TEXT(ROW()-4,"0000")) -> T0002 | B6: 2026-01-02 | C6: Checking - Bank A | D6: Whole Foods | E6: Groceries | F6: -85.32 | G6: Normal | H6: 0 | I6: =IF(F6="","",F6+H6) -> -85.32 | L6: =IF(B6="","",TEXT(B6,"YYYY-MM")) -> 2026-01 | M6: =IF($E6="","",IFERROR(VLOOKUP($E6,Categories!$A:$B,2,FALSE()),"")) -> Needs
A7: =IF(B7="","","T"&TEXT(ROW()-4,"0000")) -> T0003 | B7: 2026-01-03 | C7: Credit Card - Bank B | D7: Group Dinner - Tony's | E7: Dining Out | F7: -180 | G7: Pending Reimbursement | H7: 120 | I7: =IF(F7="","",F7+H7) -> -60 | K7: Paid for 4; 3 friends owe $40 each. No linking needed - see Owed to Me on Dashboard. | L7: =IF(B7="","",TEXT(B7,"YYYY-MM")) -> 2026-01 | M7: =IF($E7="","",IFERROR(VLOOKUP($E7,Categories!$A:$B,2,FALSE()),"")) -> Wants
A8: =IF(B8="","","T"&TEXT(ROW()-4,"0000")) -> T0004 | B8: 2026-01-05 | C8: Cash / Venmo (unlinked) | D8: Venmo from Sam & Alex | E8: Reimbursement | F8: 80 | G8: Normal | H8: 0 | I8: =IF(F8="","",F8+H8) -> 80 | K8: Repayment for Tony's dinner, landed in an unlinked account - still counts, no linking required | L8: =IF(B8="","",TEXT(B8,"YYYY-MM")) -> 2026-01 | M8: =IF($E8="","",IFERROR(VLOOKUP($E8,Categories!$A:$B,2,FALSE()),"")) -> Transfer
A9: =IF(B9="","","T"&TEXT(ROW()-4,"0000")) -> T0005 | B9: 2026-01-05 | C9: Checking - Bank A | D9: Transfer to Savings | E9: Internal Transfer | F9: -500 | G9: Normal | H9: 0 | I9: =IF(F9="","",F9+H9) -> -500 | K9: Outgoing leg of a plain account-to-account transfer - fully disregarded | L9: =IF(B9="","",TEXT(B9,"YYYY-MM")) -> 2026-01 | M9: =IF($E9="","",IFERROR(VLOOKUP($E9,Categories!$A:$B,2,FALSE()),"")) -> Transfer
A10: =IF(B10="","","T"&TEXT(ROW()-4,"0000")) -> T0006 | B10: 2026-01-05 | C10: Savings - Bank A | D10: Transfer from Checking | E10: Internal Transfer | F10: 500 | G10: Normal | H10: 0 | I10: =IF(F10="","",F10+H10) -> 500 | K10: Incoming leg - also disregarded, net effect on spending is zero | L10: =IF(B10="","",TEXT(B10,"YYYY-MM")) -> 2026-01 | M10: =IF($E10="","",IFERROR(VLOOKUP($E10,Categories!$A:$B,2,FALSE()),"")) -> Transfer
A11: =IF(B11="","","T"&TEXT(ROW()-4,"0000")) -> T0007 | B11: 2026-01-06 | C11: Checking - Bank A | D11: Auto-transfer to Brokerage | E11: Investing | F11: -600 | G11: Normal | H11: 0 | I11: =IF(F11="","",F11+H11) -> -600 | K11: This leg IS kept - it counts toward the Savings group | L11: =IF(B11="","",TEXT(B11,"YYYY-MM")) -> 2026-01 | M11: =IF($E11="","",IFERROR(VLOOKUP($E11,Categories!$A:$B,2,FALSE()),"")) -> Savings
A12: =IF(B12="","","T"&TEXT(ROW()-4,"0000")) -> T0008 | B12: 2026-01-07 | C12: Savings - Bank A | D12: Interest Paid | E12: Other Income | F12: 12.4 | G12: Normal | H12: 0 | I12: =IF(F12="","",F12+H12) -> 12.4 | L12: =IF(B12="","",TEXT(B12,"YYYY-MM")) -> 2026-01 | M12: =IF($E12="","",IFERROR(VLOOKUP($E12,Categories!$A:$B,2,FALSE()),"")) -> Income
A13: =IF(B13="","","T"&TEXT(ROW()-4,"0000")) -> T0009 | B13: 2026-01-08 | C13: Credit Card - Bank B | D13: Random one-off purchase | E13: Miscellaneous Expenses | F13: -22 | G13: Normal | H13: 0 | I13: =IF(F13="","",F13+H13) -> -22 | L13: =IF(B13="","",TEXT(B13,"YYYY-MM")) -> 2026-01 | M13: =IF($E13="","",IFERROR(VLOOKUP($E13,Categories!$A:$B,2,FALSE()),"")) -> Wants
A14: =IF(B14="","","T"&TEXT(ROW()-4,"0000")) | I14: =IF(F14="","",F14+H14) | L14: =IF(B14="","",TEXT(B14,"YYYY-MM")) | M14: =IF($E14="","",IFERROR(VLOOKUP($E14,Categories!$A:$B,2,FALSE()),""))
A15: =IF(B15="","","T"&TEXT(ROW()-4,"0000")) | I15: =IF(F15="","",F15+H15) | L15: =IF(B15="","",TEXT(B15,"YYYY-MM")) | M15: =IF($E15="","",IFERROR(VLOOKUP($E15,Categories!$A:$B,2,FALSE()),""))
A16: =IF(B16="","","T"&TEXT(ROW()-4,"0000")) | I16: =IF(F16="","",F16+H16) | L16: =IF(B16="","",TEXT(B16,"YYYY-MM")) | M16: =IF($E16="","",IFERROR(VLOOKUP($E16,Categories!$A:$B,2,FALSE()),""))
A17: =IF(B17="","","T"&TEXT(ROW()-4,"0000")) | I17: =IF(F17="","",F17+H17) | L17: =IF(B17="","",TEXT(B17,"YYYY-MM")) | M17: =IF($E17="","",IFERROR(VLOOKUP($E17,Categories!$A:$B,2,FALSE()),""))
A18: =IF(B18="","","T"&TEXT(ROW()-4,"0000")) | I18: =IF(F18="","",F18+H18) | L18: =IF(B18="","",TEXT(B18,"YYYY-MM")) | M18: =IF($E18="","",IFERROR(VLOOKUP($E18,Categories!$A:$B,2,FALSE()),""))
A19: =IF(B19="","","T"&TEXT(ROW()-4,"0000")) | I19: =IF(F19="","",F19+H19) | L19: =IF(B19="","",TEXT(B19,"YYYY-MM")) | M19: =IF($E19="","",IFERROR(VLOOKUP($E19,Categories!$A:$B,2,FALSE()),""))
A20: =IF(B20="","","T"&TEXT(ROW()-4,"0000")) | I20: =IF(F20="","",F20+H20) | L20: =IF(B20="","",TEXT(B20,"YYYY-MM")) | M20: =IF($E20="","",IFERROR(VLOOKUP($E20,Categories!$A:$B,2,FALSE()),""))
A21: =IF(B21="","","T"&TEXT(ROW()-4,"0000")) | I21: =IF(F21="","",F21+H21) | L21: =IF(B21="","",TEXT(B21,"YYYY-MM")) | M21: =IF($E21="","",IFERROR(VLOOKUP($E21,Categories!$A:$B,2,FALSE()),""))
A22: =IF(B22="","","T"&TEXT(ROW()-4,"0000")) | I22: =IF(F22="","",F22+H22) | L22: =IF(B22="","",TEXT(B22,"YYYY-MM")) | M22: =IF($E22="","",IFERROR(VLOOKUP($E22,Categories!$A:$B,2,FALSE()),""))
A23: =IF(B23="","","T"&TEXT(ROW()-4,"0000")) | I23: =IF(F23="","",F23+H23) | L23: =IF(B23="","",TEXT(B23,"YYYY-MM")) | M23: =IF($E23="","",IFERROR(VLOOKUP($E23,Categories!$A:$B,2,FALSE()),""))
A24: =IF(B24="","","T"&TEXT(ROW()-4,"0000")) | I24: =IF(F24="","",F24+H24) | L24: =IF(B24="","",TEXT(B24,"YYYY-MM")) | M24: =IF($E24="","",IFERROR(VLOOKUP($E24,Categories!$A:$B,2,FALSE()),""))
A25: =IF(B25="","","T"&TEXT(ROW()-4,"0000")) | I25: =IF(F25="","",F25+H25) | L25: =IF(B25="","",TEXT(B25,"YYYY-MM")) | M25: =IF($E25="","",IFERROR(VLOOKUP($E25,Categories!$A:$B,2,FALSE()),""))
... A500: =IF(B500="","","T"&TEXT(ROW()-4,"0000")) | I500: =IF(F500="","",F500+H500) | L500: =IF(B500="","",TEXT(B500,"YYYY-MM")) | M500: =IF($E500="","",IFERROR(VLOOKUP($E500,Categories!$A:$B,2,FALSE()),""))

Sheet Categories
A1: Categories & Budgets
A2: Needs/Wants categories (rows 5-15) feed the budget table & Needs/Wants/Savings split. 'Reimbursement' and 'Internal Transfer' are always excluded from spending/income totals.
A4: Category | B4: Group | C4: Monthly Budget
A5: Groceries | B5: Needs | C5: 500
A6: Dining Out | B6: Wants | C6: 200
A7: Transport | B7: Needs | C7: 150
A8: Rent/Mortgage | B8: Needs | C8: 1800
A9: Utilities | B9: Needs | C9: 200
A10: Entertainment | B10: Wants | C10: 100
A11: Shopping | B11: Wants | C11: 150
A12: Health | B12: Needs | C12: 100
A13: Travel | B13: Wants | C13: 100
A14: Subscriptions | B14: Wants | C14: 50
A15: Miscellaneous Expenses | B15: Wants | C15: 100
A16: Salary | B16: Income | C16: 6000
... A21: Internal Transfer | B21: Transfer | C21: 0

Sheet Accounts
A1: Accounts
A2: Add every account you want tracked. Edit yellow cells only.
A4: Account Name | B4: Type | C4: Institution | D4: Asset or Liability | E4: Current Balance | F4: Include in Net Worth | G4: Last Updated
A5: Checking - Bank A | B5: Checking | C5: Bank A | D5: Asset | E5: 3200 | F5: Y | G5: 2026-01-01
A6: Savings - Bank A | B6: Savings | C6: Bank A | D6: Asset | E6: 12000 | F6: Y | G6: 2026-01-01
A7: Credit Card - Bank B | B7: Credit Card | C7: Bank B | D7: Liability | E7: 450 | F7: Y | G7: 2026-01-01
A8: Brokerage - Broker C | B8: Investment | C8: Broker C | D8: Asset | E8: 28000 | F8: Y | G8: 2026-01-01
A9: Cash / Venmo (unlinked) | B9: Cash | C9: N/A | D9: Asset | E9: 150 | F9: Y | G9: 2026-01-01
A48: Net Worth Summary
A49: Total Assets | B49: =SUMIFS(E5:E45,D5:D45,"Asset",F5:F45,"Y") -> 43350
A50: Total Liabilities | B50: =SUMIFS(E5:E45,D5:D45,"Liability",F5:F45,"Y") -> 450
A51: Net Worth | B51: =B49-B50 -> 42900

Sheet Net Worth History
A1: Net Worth History
A2: Row 5 always reflects today's Accounts balances. Copy Row 5's values (paste as values) into a new row below whenever you want to snapshot a point in time.
A4: Date | B4: Total Assets | C4: Total Liabilities | D4: Net Worth
A5: =TODAY() -> 46259 | B5: =Accounts!$B$49 -> 43350 | C5: =Accounts!$B$50 -> 450 | D5: =B5-C5 -> 42900
A6: 2025-12-01 | B6: 40200 | C6: 11200 | D6: =B6-C6 -> 29000
D7: =IF(B7="","",B7-C7)
D8: =IF(B8="","",B8-C8)
D9: =IF(B9="","",B9-C9)
D10: =IF(B10="","",B10-C10)
D11: =IF(B11="","",B11-C11)
D12: =IF(B12="","",B12-C12)
D13: =IF(B13="","",B13-C13)
D14: =IF(B14="","",B14-C14)
D15: =IF(B15="","",B15-C15)
D16: =IF(B16="","",B16-C16)
D17: =IF(B17="","",B17-C17)
D18: =IF(B18="","",B18-C18)
... D300: =IF(B300="","",B300-C300)
